sitemap_url_parser/StartOverScraper.py
sitemap_url_parser/__init__.py
sitemap_url_parser-0.1.1.dist-info/METADATA
sitemap_url_parser-0.1.1.dist-info/WHEEL
sitemap_url_parser-0.1.1.dist-info/RECORD
