Metadata-Version: 2.1
Name: sitemap-url-parser
Version: 0.1.1
Summary: 
Author: Satyam Singh
Author-email: stmsng2001@gmail.com
Requires-Python: >=3.9,<4.0
Classifier: Programming Language :: Python :: 3
Classifier: Programming Language :: Python :: 3.9
Classifier: Programming Language :: Python :: 3.10
Classifier: Programming Language :: Python :: 3.11
Classifier: Programming Language :: Python :: 3.12
Requires-Dist: requests (>=2.32.3,<3.0.0)
Requires-Dist: setuptools (>=74.1.0,<75.0.0)
Requires-Dist: wheel (>=0.44.0,<0.45.0)
Requires-Dist: xmltodict (>=0.13.0,<0.14.0)
